voiager/__init__.py
voiager/__main__.py
voiager/datalib.py
voiager/launch.py
voiager/plotlib.py
voiager/voiager.py
Voiager-1.0.0.dist-info/LICENSE
Voiager-1.0.0.dist-info/METADATA
Voiager-1.0.0.dist-info/WHEEL
Voiager-1.0.0.dist-info/entry_points.txt
Voiager-1.0.0.dist-info/top_level.txt
Voiager-1.0.0.dist-info/RECORD
