Metadata-Version: 2.1
Name: Voiager
Version: 1.0.0
Summary: Perform cosmological analyses using voids identified in large-scale structure survey data
Home-page: https://github.com/nhamaus/Voiager
Author: Nico Hamaus
Author-email: nhamaus@gmail.com
License: MIT
Classifier: Intended Audience :: Science/Research
Classifier: Topic :: Scientific/Engineering :: Astronomy
Classifier: Programming Language :: Python :: 3
License-File: LICENSE
Requires-Dist: astropy
Requires-Dist: cython
Requires-Dist: emcee
Requires-Dist: getdist
Requires-Dist: h5py
Requires-Dist: healpy
Requires-Dist: matplotlib
Requires-Dist: numpy
Requires-Dist: pyabel
Requires-Dist: pyyaml
Requires-Dist: scipy
Requires-Dist: tqdm
Requires-Dist: vide
